julianpy_themeatly2/__init__.py
julianpy_themeatly2/julianpy.py
julianpy_themeatly2-0.1.5.dist-info/METADATA
julianpy_themeatly2-0.1.5.dist-info/WHEEL
julianpy_themeatly2-0.1.5.dist-info/licenses/LICENSE
julianpy_themeatly2-0.1.5.dist-info/RECORD
