Metadata-Version: 2.3
Name: julianpy_themeatly2
Version: 0.1.5
Summary: An API for Julian's Editor
Project-URL: Homepage, https://github.com/pypa/sampleproject
Project-URL: Issues, https://github.com/pypa/sampleproject/issues
Author-email: Themeatly2 <themeatly2@themeatly2.top>, Harsizcool <harsizstudio@gmail.com>
Classifier: License :: OSI Approved :: MIT License
Classifier: Operating System :: OS Independent
Classifier: Programming Language :: Python :: 3
Requires-Python: >=3.8
Requires-Dist: pyautogui
Requires-Dist: selenium
